PythonDefense/__init__.py
PythonDefense/enemy.py
PythonDefense/helper_functions.py
PythonDefense/main.py
PythonDefense/player.py
PythonDefense/projectile.py
PythonDefense/round.py
PythonDefense/tower.py
PythonDefense/assets/Fonts/OpenSans-Regular.ttf
PythonDefense/assets/buttons/bt-start.png
PythonDefense/assets/buttons/bt-upgrade-red.jpg
PythonDefense/assets/buttons/hilite.png
PythonDefense/assets/enemies/enemy1.png
PythonDefense/assets/enemies/enemy2.png
PythonDefense/assets/enemies/enemy3.png
PythonDefense/assets/levels/num1.png
PythonDefense/assets/levels/num2.png
PythonDefense/assets/levels/num3.png
PythonDefense/assets/levels/num4.png
PythonDefense/assets/levels/num5.png
PythonDefense/assets/projectiles/fireball.png
PythonDefense/assets/tiles/dirt_tile.png
PythonDefense/assets/tiles/grass_tile.png
PythonDefense/assets/tiles/menu_tile.png
PythonDefense/assets/towers/tower1.png
PythonDefense/assets/towers/tower2.png
PythonDefense/assets/towers/tower3.png
PythonDefense/assets/towers/tower4.png
PythonDefense/assets/towers/tower5.png
PythonDefense-1.0.3.dist-info/METADATA
PythonDefense-1.0.3.dist-info/WHEEL
PythonDefense-1.0.3.dist-info/entry_points.txt
PythonDefense-1.0.3.dist-info/top_level.txt
PythonDefense-1.0.3.dist-info/RECORD
