Metadata-Version: 2.1
Name: PythonDefense
Version: 1.0.3
Summary: Tower defense game written in python
Home-page: https://github.com/mwalmer/Python-Defense
Author: Alex Skladanek, Amer  Khalifa, Benjamin Coretese, Eric Weisfeld, Maxwell Walmer
License: UNKNOWN
Platform: UNKNOWN
Requires-Dist: pygame (~=2.0.1)
